{
  "dark": {
    "activeColor": "#bd93f9",
    "activeFull": "rgba(189, 147, 249, 0.95)",
    "activeLight": "rgba(189, 147, 249, 0.25)",
    "activeMedium": "rgba(189, 147, 249, 0.35)",
    "activeSubtle": "rgba(189, 147, 249, 0.15)",
    "bgCard": "rgba(40, 42, 54, 0.60)",
    "bgColor": "#282a36",
    "bgElevated": "#363949",
    "bgElevatedAlt": "#323444",
    "bgElevatedHover": "#3b3e4f",
    "bgInput": "rgba(40, 42, 54, 0.80)",
    "bgOverlay": "rgba(0, 0, 0, 0.50)",
    "bgSubtle": "rgba(40, 42, 54, 0.15)",
    "borderColor": "#44475a",
    "borderLight": "rgba(68, 71, 90, 0.25)",
    "borderMedium": "rgba(68, 71, 90, 0.40)",
    "borderStrong": "rgba(68, 71, 90, 0.50)",
    "borderSubtle": "rgba(68, 71, 90, 0.22)",
    "critical": "#ff5555",
    "disabledColor": "#343746",
    "inactiveColor": "#6272a4",
    "onHoverColor": "#ff79c6",
    "panelWindowColor": "transparent",
    "powerSaveColor": "#50fa7b",
    "shadowColor": "rgba(0, 0, 0, 0.20)",
    "shadowColorStrong": "rgba(0, 0, 0, 0.55)",
    "textActiveColor": "#f8f8f2",
    "textDisabled": "rgba(98, 114, 164, 0.35)",
    "textInactiveColor": "#6272a4",
    "textOnHoverColor": "#8be9fd",
    "warning": "#f1fa8c"
  },
  "light": {
    "activeColor": "#8332f4",
    "activeFull": "rgba(131, 50, 244, 0.95)",
    "activeLight": "rgba(131, 50, 244, 0.25)",
    "activeMedium": "rgba(131, 50, 244, 0.35)",
    "activeSubtle": "rgba(131, 50, 244, 0.15)",
    "bgCard": "rgba(248, 248, 242, 0.60)",
    "bgColor": "#f8f8f2",
    "bgElevated": "#ffffff",
    "bgElevatedAlt": "#ffffff",
    "bgElevatedHover": "#ffffff",
    "bgInput": "rgba(248, 248, 242, 0.80)",
    "bgOverlay": "rgba(0, 0, 0, 0.50)",
    "bgSubtle": "rgba(248, 248, 242, 0.15)",
    "borderColor": "#e6e6ea",
    "borderLight": "rgba(230, 230, 234, 0.25)",
    "borderMedium": "rgba(230, 230, 234, 0.40)",
    "borderStrong": "rgba(230, 230, 234, 0.50)",
    "borderSubtle": "rgba(230, 230, 234, 0.22)",
    "critical": "#ff5555",
    "disabledColor": "#d6d8e0",
    "inactiveColor": "#44475a",
    "onHoverColor": "#ff1399",
    "panelWindowColor": "transparent",
    "powerSaveColor": "#22d87d",
    "shadowColor": "rgba(0, 0, 0, 0.20)",
    "shadowColorStrong": "rgba(0, 0, 0, 0.55)",
    "textActiveColor": "#282a36",
    "textDisabled": "rgba(68, 71, 90, 0.35)",
    "textInactiveColor": "#44475a",
    "textOnHoverColor": "#ff79c6",
    "warning": "#f1fa8c"
  }
}
